ashare_reader/DailyDataReader.py
ashare_reader/DailyReader.py
ashare_reader/StockListFetcher_SZ.py
ashare_reader/TxtReader.py
ashare_reader/__init__.py
ashare_reader/py.typed
ashare_reader-0.5.1.dist-info/METADATA
ashare_reader-0.5.1.dist-info/WHEEL
ashare_reader-0.5.1.dist-info/RECORD
