Metadata-Version: 2.4
Name: ashare-reader
Version: 0.5.1
Summary: 读取本地股票数据
Author-email: zw <szzend@qq.com>
Requires-Python: >=3.12
Requires-Dist: httpx[http2]>=0.28.1
Requires-Dist: openpyxl>=3.1.5
Requires-Dist: pandas>=2.2.3
Requires-Dist: pyarrow>=19.0.1
